flask_tinyauth/__init__.py
flask_tinyauth/api.py
flask_tinyauth/authorize.py
flask_tinyauth/exceptions.py
flask_tinyauth/login.py
flask_tinyauth/redirect.py
flask_tinyauth/static/main.b9228724.js
flask_tinyauth/templates/frontend/login.html
flask_tinyauth/tests/__init__.py
flask_tinyauth/tests/test_authorize.py
flask_tinyauth/tests/test_login.py
flask_tinyauth-0.0.2.dist-info/DESCRIPTION.rst
flask_tinyauth-0.0.2.dist-info/METADATA
flask_tinyauth-0.0.2.dist-info/RECORD
flask_tinyauth-0.0.2.dist-info/WHEEL
flask_tinyauth-0.0.2.dist-info/metadata.json
flask_tinyauth-0.0.2.dist-info/top_level.txt
