Metadata-Version: 2.0
Name: flask-tinyauth
Version: 0.0.2
Summary: UNKNOWN
Home-page: UNKNOWN
Author: UNKNOWN
Author-email: UNKNOWN
License: Apache Software License
Platform: UNKNOWN
Classifier: Operating System :: POSIX
Classifier: License :: OSI Approved :: Apache Software License
Classifier: Programming Language :: Python :: 3
Classifier: Programming Language :: Python :: 3.6
Classifier: Programming Language :: Python :: Implementation :: CPython
Requires-Dist: requests
Requires-Dist: flask-restful
Provides-Extra: test
Requires-Dist: flake8; extra == 'test'
Requires-Dist: flake8-isort; extra == 'test'
Requires-Dist: pytest; extra == 'test'
Requires-Dist: pytest-cov; extra == 'test'
Requires-Dist: codecov; extra == 'test'
